IReadiTunes/IReadiTunes.py
IReadiTunes/__init__.py
IReadiTunes-1.0.5.dist-info/LICENSE
IReadiTunes-1.0.5.dist-info/METADATA
IReadiTunes-1.0.5.dist-info/WHEEL
IReadiTunes-1.0.5.dist-info/top_level.txt
IReadiTunes-1.0.5.dist-info/RECORD
