Metadata-Version: 2.1
Name: IReadiTunes
Version: 1.0.5
Summary: Tool to get any information about iTunes tracks and playlists quickly and easily
Home-page: https://github.com/mickael2054/IReadiTunes
Author: Mickael
Author-email: mickael2054dev@gmail.com
License: MIT
Platform: UNKNOWN
Classifier: Programming Language :: Python :: 3.5
Classifier: Operating System :: OS Independent
Classifier: Topic :: Utilities
License-File: LICENSE
